lsprofcalltree.py
setup.py
lpct.egg-info/PKG-INFO
lpct.egg-info/SOURCES.txt
lpct.egg-info/dependency_links.txt
lpct.egg-info/entry_points.txt
lpct.egg-info/top_level.txt