Metadata-Version: 1.0
Name: lpct
Version: 0.9
Summary: lsprof output which is readable by kcachegrind
Home-page: https://github.com/pwaller/lpct
Author: David Allouche, Jp Calderone, Itamar Shtull-Trauring and Johan Dahlin; modified by Peter Waller
Author-email: p@pwaller.net
License: UNKNOWN
Platform: UNKNOWN
